{"loss": 0.06515754759311676, "timestamp": 1742733975, "checkpoint_dir_name": null, "done": false, "training_iteration": 1, "trial_id": "dfdca_02865", "date": "2025-03-23_05-46-15", "time_this_iter_s": 6.228782653808594, "time_total_s": 6.228782653808594, "pid": 8916, "hostname": "PS2023NAHFSMES", "node_ip": "127.0.0.1", "config": {"learning_rate": 0.0007535014124895449, "num_heads": 2, "dropout_rate": 0.4219361311205221, "num_layers": 3, "ff_dim": 128, "batch_size": 64, "l2_reg": 0.0007728032325182345, "lookback": 30, "sequence_length": 30}, "time_since_restore": 6.228782653808594, "iterations_since_restore": 1}
{"loss": 0.06515754759311676, "timestamp": 1742733975, "checkpoint_dir_name": null, "done": false, "training_iteration": 2, "trial_id": "dfdca_02865", "date": "2025-03-23_05-46-15", "time_this_iter_s": 0.0014214515686035156, "time_total_s": 6.230204105377197, "pid": 8916, "hostname": "PS2023NAHFSMES", "node_ip": "127.0.0.1", "config": {"learning_rate": 0.0007535014124895449, "num_heads": 2, "dropout_rate": 0.4219361311205221, "num_layers": 3, "ff_dim": 128, "batch_size": 64, "l2_reg": 0.0007728032325182345, "lookback": 30, "sequence_length": 30}, "time_since_restore": 6.230204105377197, "iterations_since_restore": 2}
