{"loss": 0.7669469714164734, "timestamp": 1741854695, "checkpoint_dir_name": null, "done": false, "training_iteration": 1, "trial_id": "4ec47_00086", "date": "2025-03-13_01-31-35", "time_this_iter_s": 8.466837167739868, "time_total_s": 8.466837167739868, "pid": 18856, "hostname": "PS2023NAHFSMES", "node_ip": "127.0.0.1", "config": {"learning_rate": 4.904878605928425e-05, "num_heads": 8, "dropout_rate": 0.47819148323865235, "num_layers": 2, "ff_dim": 128, "batch_size": 16, "l2_reg": 0.000563768376188061}, "time_since_restore": 8.466837167739868, "iterations_since_restore": 1}
