{"loss": 0.6690376996994019, "timestamp": 1742320457, "checkpoint_dir_name": null, "done": false, "training_iteration": 1, "trial_id": "19edf_00028", "date": "2025-03-18_10-54-17", "time_this_iter_s": 14.184447288513184, "time_total_s": 14.184447288513184, "pid": 28544, "hostname": "PS2023NAHFSMES", "node_ip": "127.0.0.1", "config": {"learning_rate": 1.5023881774513822e-06, "num_heads": 2, "dropout_rate": 0.19705731090944983, "num_layers": 1, "ff_dim": 512, "batch_size": 32, "l2_reg": 0.0002655880751262464, "lookback": 30, "sequence_length": 30}, "time_since_restore": 14.184447288513184, "iterations_since_restore": 1}
{"loss": 0.6690376996994019, "timestamp": 1742320457, "checkpoint_dir_name": null, "done": false, "training_iteration": 2, "trial_id": "19edf_00028", "date": "2025-03-18_10-54-17", "time_this_iter_s": 0.0010182857513427734, "time_total_s": 14.185465574264526, "pid": 28544, "hostname": "PS2023NAHFSMES", "node_ip": "127.0.0.1", "config": {"learning_rate": 1.5023881774513822e-06, "num_heads": 2, "dropout_rate": 0.19705731090944983, "num_layers": 1, "ff_dim": 512, "batch_size": 32, "l2_reg": 0.0002655880751262464, "lookback": 30, "sequence_length": 30}, "time_since_restore": 14.185465574264526, "iterations_since_restore": 2}
