{"loss": 0.8424027562141418, "timestamp": 1742185962, "checkpoint_dir_name": null, "done": false, "training_iteration": 1, "trial_id": "b002c_00004", "date": "2025-03-16_21-32-42", "time_this_iter_s": 2.316183567047119, "time_total_s": 2.316183567047119, "pid": 30520, "hostname": "PS2023NAHFSMES", "node_ip": "127.0.0.1", "config": {"learning_rate": 2.1623973746520106e-06, "num_heads": 2, "dropout_rate": 0.15950147856868652, "num_layers": 1, "ff_dim": 512, "batch_size": 32, "l2_reg": 0.0002580483365538712, "lookback": 30, "sequence_length": 30}, "time_since_restore": 2.316183567047119, "iterations_since_restore": 1}
{"loss": 0.8424027562141418, "timestamp": 1742185962, "checkpoint_dir_name": null, "done": false, "training_iteration": 2, "trial_id": "b002c_00004", "date": "2025-03-16_21-32-42", "time_this_iter_s": 0.0011286735534667969, "time_total_s": 2.317312240600586, "pid": 30520, "hostname": "PS2023NAHFSMES", "node_ip": "127.0.0.1", "config": {"learning_rate": 2.1623973746520106e-06, "num_heads": 2, "dropout_rate": 0.15950147856868652, "num_layers": 1, "ff_dim": 512, "batch_size": 32, "l2_reg": 0.0002580483365538712, "lookback": 30, "sequence_length": 30}, "time_since_restore": 2.317312240600586, "iterations_since_restore": 2}
