{"loss": 0.21121259033679962, "timestamp": 1742322562, "checkpoint_dir_name": null, "done": false, "training_iteration": 1, "trial_id": "19edf_00182", "date": "2025-03-18_11-29-22", "time_this_iter_s": 2.2842116355895996, "time_total_s": 2.2842116355895996, "pid": 19676, "hostname": "PS2023NAHFSMES", "node_ip": "127.0.0.1", "config": {"learning_rate": 1.2369499641049255e-06, "num_heads": 2, "dropout_rate": 0.1974020003637377, "num_layers": 1, "ff_dim": 512, "batch_size": 32, "l2_reg": 0.00029207779858239906, "lookback": 30, "sequence_length": 30}, "time_since_restore": 2.2842116355895996, "iterations_since_restore": 1}
{"loss": 0.21121259033679962, "timestamp": 1742322562, "checkpoint_dir_name": null, "done": false, "training_iteration": 2, "trial_id": "19edf_00182", "date": "2025-03-18_11-29-22", "time_this_iter_s": 0.0, "time_total_s": 2.2842116355895996, "pid": 19676, "hostname": "PS2023NAHFSMES", "node_ip": "127.0.0.1", "config": {"learning_rate": 1.2369499641049255e-06, "num_heads": 2, "dropout_rate": 0.1974020003637377, "num_layers": 1, "ff_dim": 512, "batch_size": 32, "l2_reg": 0.00029207779858239906, "lookback": 30, "sequence_length": 30}, "time_since_restore": 2.2842116355895996, "iterations_since_restore": 2}
