{"mean_reward": 6.681715033226647, "timestamp": 1742840389, "checkpoint_dir_name": null, "done": false, "training_iteration": 1, "trial_id": "0187c_00156", "date": "2025-03-24_11-19-49", "time_this_iter_s": 600.3455851078033, "time_total_s": 600.3455851078033, "pid": 28536, "hostname": "PS2023NAHFSMES", "node_ip": "127.0.0.1", "config": {"learning_rate": 0.0005354126174055627, "batch_size": 128, "ent_coef": 0.010502389076060775, "buffer_size": 100000, "tau": 0.07591201115566801, "gamma": 0.9291475978341015}, "time_since_restore": 600.3455851078033, "iterations_since_restore": 1}
{"mean_reward": 6.681715033226647, "timestamp": 1742840389, "checkpoint_dir_name": null, "done": false, "training_iteration": 2, "trial_id": "0187c_00156", "date": "2025-03-24_11-19-49", "time_this_iter_s": 0.0011358261108398438, "time_total_s": 600.3467209339142, "pid": 28536, "hostname": "PS2023NAHFSMES", "node_ip": "127.0.0.1", "config": {"learning_rate": 0.0005354126174055627, "batch_size": 128, "ent_coef": 0.010502389076060775, "buffer_size": 100000, "tau": 0.07591201115566801, "gamma": 0.9291475978341015}, "time_since_restore": 600.3467209339142, "iterations_since_restore": 2}
