{"loss": 0.06711915135383606, "timestamp": 1742734000, "checkpoint_dir_name": null, "done": false, "training_iteration": 1, "trial_id": "dfdca_02868", "date": "2025-03-23_05-46-40", "time_this_iter_s": 4.398182392120361, "time_total_s": 4.398182392120361, "pid": 27340, "hostname": "PS2023NAHFSMES", "node_ip": "127.0.0.1", "config": {"learning_rate": 0.0007535014124895449, "num_heads": 8, "dropout_rate": 0.4219361311205221, "num_layers": 3, "ff_dim": 256, "batch_size": 64, "l2_reg": 0.0007728032325182345, "lookback": 30, "sequence_length": 30}, "time_since_restore": 4.398182392120361, "iterations_since_restore": 1}
{"loss": 0.06711915135383606, "timestamp": 1742734000, "checkpoint_dir_name": null, "done": false, "training_iteration": 2, "trial_id": "dfdca_02868", "date": "2025-03-23_05-46-40", "time_this_iter_s": 0.0010077953338623047, "time_total_s": 4.399190187454224, "pid": 27340, "hostname": "PS2023NAHFSMES", "node_ip": "127.0.0.1", "config": {"learning_rate": 0.0007535014124895449, "num_heads": 8, "dropout_rate": 0.4219361311205221, "num_layers": 3, "ff_dim": 256, "batch_size": 64, "l2_reg": 0.0007728032325182345, "lookback": 30, "sequence_length": 30}, "time_since_restore": 4.399190187454224, "iterations_since_restore": 2}
