{"loss": Infinity, "timestamp": 1742457123, "checkpoint_dir_name": null, "done": false, "training_iteration": 1, "trial_id": "94582_00358", "date": "2025-03-20_00-52-03", "time_this_iter_s": 0.1024787425994873, "time_total_s": 0.1024787425994873, "pid": 27384, "hostname": "PS2023NAHFSMES", "node_ip": "127.0.0.1", "config": {"learning_rate": 0.00015683852581586645, "num_heads": 8, "dropout_rate": 0.3394633936788146, "num_layers": 2, "ff_dim": 256, "batch_size": 64, "l2_reg": 0.0016445845403801217, "lookback": 90, "sequence_length": 30}, "time_since_restore": 0.1024787425994873, "iterations_since_restore": 1}
