{"mean_reward": -15.471388628522243, "timestamp": 1742627695, "checkpoint_dir_name": null, "done": false, "training_iteration": 1, "trial_id": "0d403_00008", "date": "2025-03-22_00-14-55", "time_this_iter_s": 579.82009100914, "time_total_s": 579.82009100914, "pid": 7712, "hostname": "PS2023NAHFSMES", "node_ip": "127.0.0.1", "config": {"learning_rate": 1.2565091201358774e-05, "batch_size": 64, "ent_coef": 0.0033404072405778746, "buffer_size": 10000, "tau": 0.04388079993666119, "gamma": 0.9309231938692146}, "time_since_restore": 579.82009100914, "iterations_since_restore": 1}
{"mean_reward": -15.471388628522243, "timestamp": 1742627695, "checkpoint_dir_name": null, "done": false, "training_iteration": 2, "trial_id": "0d403_00008", "date": "2025-03-22_00-14-55", "time_this_iter_s": 0.0, "time_total_s": 579.82009100914, "pid": 7712, "hostname": "PS2023NAHFSMES", "node_ip": "127.0.0.1", "config": {"learning_rate": 1.2565091201358774e-05, "batch_size": 64, "ent_coef": 0.0033404072405778746, "buffer_size": 10000, "tau": 0.04388079993666119, "gamma": 0.9309231938692146}, "time_since_restore": 579.82009100914, "iterations_since_restore": 2}
