{"loss": 1.7120001316070557, "timestamp": 1742145798, "checkpoint_dir_name": null, "done": false, "training_iteration": 1, "trial_id": "f261f_00058", "date": "2025-03-16_10-23-18", "time_this_iter_s": 10.420863389968872, "time_total_s": 10.420863389968872, "pid": 31792, "hostname": "PS2023NAHFSMES", "node_ip": "127.0.0.1", "config": {"learning_rate": 4.8616508677439975e-06, "num_heads": 2, "dropout_rate": 0.41108117463943233, "num_layers": 2, "ff_dim": 256, "batch_size": 128, "l2_reg": 0.00014527566697397789, "lookback": 30, "sequence_length": 30}, "time_since_restore": 10.420863389968872, "iterations_since_restore": 1}
{"loss": 1.7120001316070557, "timestamp": 1742145798, "checkpoint_dir_name": null, "done": false, "training_iteration": 2, "trial_id": "f261f_00058", "date": "2025-03-16_10-23-18", "time_this_iter_s": 0.0, "time_total_s": 10.420863389968872, "pid": 31792, "hostname": "PS2023NAHFSMES", "node_ip": "127.0.0.1", "config": {"learning_rate": 4.8616508677439975e-06, "num_heads": 2, "dropout_rate": 0.41108117463943233, "num_layers": 2, "ff_dim": 256, "batch_size": 128, "l2_reg": 0.00014527566697397789, "lookback": 30, "sequence_length": 30}, "time_since_restore": 10.420863389968872, "iterations_since_restore": 2}
