{"loss": 0.7856170535087585, "test_loss": 0.732571542263031, "timestamp": 1741948175, "checkpoint_dir_name": null, "done": false, "training_iteration": 1, "trial_id": "450d7_00492", "date": "2025-03-14_03-29-35", "time_this_iter_s": 14.383977890014648, "time_total_s": 14.383977890014648, "pid": 16536, "hostname": "PS2023NAHFSMES", "node_ip": "127.0.0.1", "config": {"learning_rate": 1.4052058773117345e-05, "num_heads": 8, "dropout_rate": 0.4795696050324163, "num_layers": 4, "ff_dim": 128, "batch_size": 16, "l2_reg": 1.3199465303060967e-05}, "time_since_restore": 14.383977890014648, "iterations_since_restore": 1}
