{"loss": 0.53841632604599, "timestamp": 1742321147, "checkpoint_dir_name": null, "done": false, "training_iteration": 1, "trial_id": "19edf_00078", "date": "2025-03-18_11-05-47", "time_this_iter_s": 8.098386526107788, "time_total_s": 8.098386526107788, "pid": 28844, "hostname": "PS2023NAHFSMES", "node_ip": "127.0.0.1", "config": {"learning_rate": 1.6884291979170639e-06, "num_heads": 2, "dropout_rate": 0.1912845277017583, "num_layers": 1, "ff_dim": 512, "batch_size": 32, "l2_reg": 0.0002474216239283948, "lookback": 30, "sequence_length": 30}, "time_since_restore": 8.098386526107788, "iterations_since_restore": 1}
{"loss": 0.53841632604599, "timestamp": 1742321147, "checkpoint_dir_name": null, "done": false, "training_iteration": 2, "trial_id": "19edf_00078", "date": "2025-03-18_11-05-47", "time_this_iter_s": 0.0012781620025634766, "time_total_s": 8.099664688110352, "pid": 28844, "hostname": "PS2023NAHFSMES", "node_ip": "127.0.0.1", "config": {"learning_rate": 1.6884291979170639e-06, "num_heads": 2, "dropout_rate": 0.1912845277017583, "num_layers": 1, "ff_dim": 512, "batch_size": 32, "l2_reg": 0.0002474216239283948, "lookback": 30, "sequence_length": 30}, "time_since_restore": 8.099664688110352, "iterations_since_restore": 2}
