{"loss": 3.4758975505828857, "test_loss": 1.4724578857421875, "timestamp": 1741940018, "checkpoint_dir_name": null, "done": false, "training_iteration": 1, "trial_id": "450d7_00087", "date": "2025-03-14_01-13-38", "time_this_iter_s": 8.789368152618408, "time_total_s": 8.789368152618408, "pid": 7892, "hostname": "PS2023NAHFSMES", "node_ip": "127.0.0.1", "config": {"learning_rate": 2.7620729976890833e-06, "num_heads": 4, "dropout_rate": 0.2908458091889836, "num_layers": 4, "ff_dim": 128, "batch_size": 64, "l2_reg": 1.4232612275752492e-05}, "time_since_restore": 8.789368152618408, "iterations_since_restore": 1}
