{"loss": 0.1570732742547989, "timestamp": 1742184068, "checkpoint_dir_name": null, "done": false, "training_iteration": 1, "trial_id": "c7592_00077", "date": "2025-03-16_21-01-08", "time_this_iter_s": 3.7514407634735107, "time_total_s": 3.7514407634735107, "pid": 25772, "hostname": "PS2023NAHFSMES", "node_ip": "127.0.0.1", "config": {"learning_rate": 5.288602387406669e-06, "num_heads": 2, "dropout_rate": 0.3141481008192072, "num_layers": 1, "ff_dim": 128, "batch_size": 32, "l2_reg": 0.0002856323778697357, "lookback": 30, "sequence_length": 30}, "time_since_restore": 3.7514407634735107, "iterations_since_restore": 1}
{"loss": 0.1570732742547989, "timestamp": 1742184068, "checkpoint_dir_name": null, "done": false, "training_iteration": 2, "trial_id": "c7592_00077", "date": "2025-03-16_21-01-08", "time_this_iter_s": 0.0, "time_total_s": 3.7514407634735107, "pid": 25772, "hostname": "PS2023NAHFSMES", "node_ip": "127.0.0.1", "config": {"learning_rate": 5.288602387406669e-06, "num_heads": 2, "dropout_rate": 0.3141481008192072, "num_layers": 1, "ff_dim": 128, "batch_size": 32, "l2_reg": 0.0002856323778697357, "lookback": 30, "sequence_length": 30}, "time_since_restore": 3.7514407634735107, "iterations_since_restore": 2}
