{"loss": 0.08277670294046402, "timestamp": 1742321748, "checkpoint_dir_name": null, "done": false, "training_iteration": 1, "trial_id": "19edf_00120", "date": "2025-03-18_11-15-48", "time_this_iter_s": 9.461251735687256, "time_total_s": 9.461251735687256, "pid": 24968, "hostname": "PS2023NAHFSMES", "node_ip": "127.0.0.1", "config": {"learning_rate": 1.8403503846824752e-06, "num_heads": 2, "dropout_rate": 0.19415831602306305, "num_layers": 1, "ff_dim": 512, "batch_size": 32, "l2_reg": 0.0002098523055779967, "lookback": 30, "sequence_length": 30}, "time_since_restore": 9.461251735687256, "iterations_since_restore": 1}
{"loss": 0.08277670294046402, "timestamp": 1742321748, "checkpoint_dir_name": null, "done": false, "training_iteration": 2, "trial_id": "19edf_00120", "date": "2025-03-18_11-15-48", "time_this_iter_s": 0.0, "time_total_s": 9.461251735687256, "pid": 24968, "hostname": "PS2023NAHFSMES", "node_ip": "127.0.0.1", "config": {"learning_rate": 1.8403503846824752e-06, "num_heads": 2, "dropout_rate": 0.19415831602306305, "num_layers": 1, "ff_dim": 512, "batch_size": 32, "l2_reg": 0.0002098523055779967, "lookback": 30, "sequence_length": 30}, "time_since_restore": 9.461251735687256, "iterations_since_restore": 2}
