{"loss": 0.6669500470161438, "test_loss": 0.6165151000022888, "timestamp": 1741943944, "checkpoint_dir_name": null, "done": false, "training_iteration": 1, "trial_id": "450d7_00286", "date": "2025-03-14_02-19-04", "time_this_iter_s": 13.900501728057861, "time_total_s": 13.900501728057861, "pid": 15592, "hostname": "PS2023NAHFSMES", "node_ip": "127.0.0.1", "config": {"learning_rate": 6.27173691951534e-05, "num_heads": 2, "dropout_rate": 0.17869584161829707, "num_layers": 4, "ff_dim": 256, "batch_size": 32, "l2_reg": 4.518062877008464e-06}, "time_since_restore": 13.900501728057861, "iterations_since_restore": 1}
