{"loss": 0.6565772891044617, "test_loss": 0.5853005647659302, "timestamp": 1741939870, "checkpoint_dir_name": null, "done": false, "training_iteration": 1, "trial_id": "450d7_00078", "date": "2025-03-14_01-11-10", "time_this_iter_s": 15.230742692947388, "time_total_s": 15.230742692947388, "pid": 24260, "hostname": "PS2023NAHFSMES", "node_ip": "127.0.0.1", "config": {"learning_rate": 1.4814052777826059e-05, "num_heads": 4, "dropout_rate": 0.20945656697332382, "num_layers": 2, "ff_dim": 256, "batch_size": 32, "l2_reg": 1.2763201826037582e-06}, "time_since_restore": 15.230742692947388, "iterations_since_restore": 1}
