{"loss": 0.10625843703746796, "timestamp": 1742478254, "checkpoint_dir_name": null, "done": false, "training_iteration": 1, "trial_id": "37015_01991", "date": "2025-03-20_06-44-14", "time_this_iter_s": 2.5797903537750244, "time_total_s": 2.5797903537750244, "pid": 22520, "hostname": "PS2023NAHFSMES", "node_ip": "127.0.0.1", "config": {"learning_rate": 8.742861711723645e-05, "num_heads": 4, "dropout_rate": 0.1643137345031403, "num_layers": 2, "ff_dim": 256, "batch_size": 64, "l2_reg": 0.0040506187898287265, "lookback": 30, "sequence_length": 30}, "time_since_restore": 2.5797903537750244, "iterations_since_restore": 1}
{"loss": 0.10625843703746796, "timestamp": 1742478254, "checkpoint_dir_name": null, "done": false, "training_iteration": 2, "trial_id": "37015_01991", "date": "2025-03-20_06-44-14", "time_this_iter_s": 0.0013697147369384766, "time_total_s": 2.581160068511963, "pid": 22520, "hostname": "PS2023NAHFSMES", "node_ip": "127.0.0.1", "config": {"learning_rate": 8.742861711723645e-05, "num_heads": 4, "dropout_rate": 0.1643137345031403, "num_layers": 2, "ff_dim": 256, "batch_size": 64, "l2_reg": 0.0040506187898287265, "lookback": 30, "sequence_length": 30}, "time_since_restore": 2.581160068511963, "iterations_since_restore": 2}
