{"loss": 0.2238115817308426, "timestamp": 1742184021, "checkpoint_dir_name": null, "done": false, "training_iteration": 1, "trial_id": "c7592_00072", "date": "2025-03-16_21-00-21", "time_this_iter_s": 3.130779981613159, "time_total_s": 3.130779981613159, "pid": 31704, "hostname": "PS2023NAHFSMES", "node_ip": "127.0.0.1", "config": {"learning_rate": 0.0009704778298169043, "num_heads": 8, "dropout_rate": 0.14322877772565057, "num_layers": 2, "ff_dim": 512, "batch_size": 32, "l2_reg": 1.963831752954893e-05, "lookback": 30, "sequence_length": 30}, "time_since_restore": 3.130779981613159, "iterations_since_restore": 1}
{"loss": 0.2238115817308426, "timestamp": 1742184021, "checkpoint_dir_name": null, "done": false, "training_iteration": 2, "trial_id": "c7592_00072", "date": "2025-03-16_21-00-21", "time_this_iter_s": 0.0010857582092285156, "time_total_s": 3.1318657398223877, "pid": 31704, "hostname": "PS2023NAHFSMES", "node_ip": "127.0.0.1", "config": {"learning_rate": 0.0009704778298169043, "num_heads": 8, "dropout_rate": 0.14322877772565057, "num_layers": 2, "ff_dim": 512, "batch_size": 32, "l2_reg": 1.963831752954893e-05, "lookback": 30, "sequence_length": 30}, "time_since_restore": 3.1318657398223877, "iterations_since_restore": 2}
