{"loss": 0.1358100324869156, "timestamp": 1742182598, "checkpoint_dir_name": null, "done": false, "training_iteration": 1, "trial_id": "5ad74_00070", "date": "2025-03-16_20-36-38", "time_this_iter_s": 2.8868603706359863, "time_total_s": 2.8868603706359863, "pid": 21864, "hostname": "PS2023NAHFSMES", "node_ip": "127.0.0.1", "config": {"learning_rate": 3.2145000644867255e-05, "num_heads": 8, "dropout_rate": 0.41149771663058954, "num_layers": 3, "ff_dim": 128, "batch_size": 64, "l2_reg": 0.00020503413726217565, "lookback": 30, "sequence_length": 30}, "time_since_restore": 2.8868603706359863, "iterations_since_restore": 1}
{"loss": 0.1358100324869156, "timestamp": 1742182598, "checkpoint_dir_name": null, "done": false, "training_iteration": 2, "trial_id": "5ad74_00070", "date": "2025-03-16_20-36-38", "time_this_iter_s": 0.0, "time_total_s": 2.8868603706359863, "pid": 21864, "hostname": "PS2023NAHFSMES", "node_ip": "127.0.0.1", "config": {"learning_rate": 3.2145000644867255e-05, "num_heads": 8, "dropout_rate": 0.41149771663058954, "num_layers": 3, "ff_dim": 128, "batch_size": 64, "l2_reg": 0.00020503413726217565, "lookback": 30, "sequence_length": 30}, "time_since_restore": 2.8868603706359863, "iterations_since_restore": 2}
