{"mean_reward": 6.67642791607359, "timestamp": 1742775912, "checkpoint_dir_name": null, "done": false, "training_iteration": 1, "trial_id": "0187c_00049", "date": "2025-03-23_17-25-12", "time_this_iter_s": 587.6394157409668, "time_total_s": 587.6394157409668, "pid": 7548, "hostname": "PS2023NAHFSMES", "node_ip": "127.0.0.1", "config": {"learning_rate": 0.0009633492794077778, "batch_size": 512, "ent_coef": 0.001862771626928597, "buffer_size": 100000, "tau": 0.037536579882283067, "gamma": 0.9796337232982881}, "time_since_restore": 587.6394157409668, "iterations_since_restore": 1}
{"mean_reward": 6.67642791607359, "timestamp": 1742775912, "checkpoint_dir_name": null, "done": false, "training_iteration": 2, "trial_id": "0187c_00049", "date": "2025-03-23_17-25-12", "time_this_iter_s": 0.0014102458953857422, "time_total_s": 587.6408259868622, "pid": 7548, "hostname": "PS2023NAHFSMES", "node_ip": "127.0.0.1", "config": {"learning_rate": 0.0009633492794077778, "batch_size": 512, "ent_coef": 0.001862771626928597, "buffer_size": 100000, "tau": 0.037536579882283067, "gamma": 0.9796337232982881}, "time_since_restore": 587.6408259868622, "iterations_since_restore": 2}
