{"loss": 0.6947988271713257, "test_loss": 0.5986208915710449, "timestamp": 1741936946, "checkpoint_dir_name": null, "done": false, "training_iteration": 1, "trial_id": "aa7b4_00008", "date": "2025-03-14_00-22-26", "time_this_iter_s": 10.55201005935669, "time_total_s": 10.55201005935669, "pid": 10272, "hostname": "PS2023NAHFSMES", "node_ip": "127.0.0.1", "config": {"learning_rate": 9.86204209934008e-06, "num_heads": 8, "dropout_rate": 0.14917236969905032, "num_layers": 2, "ff_dim": 512, "batch_size": 16, "l2_reg": 1.8294005454286044e-06}, "time_since_restore": 10.55201005935669, "iterations_since_restore": 1}
