{"loss": 0.6197577714920044, "timestamp": 1742322832, "checkpoint_dir_name": null, "done": false, "training_iteration": 1, "trial_id": "19edf_00203", "date": "2025-03-18_11-33-52", "time_this_iter_s": 2.2837905883789062, "time_total_s": 2.2837905883789062, "pid": 32364, "hostname": "PS2023NAHFSMES", "node_ip": "127.0.0.1", "config": {"learning_rate": 1.059948063412498e-06, "num_heads": 2, "dropout_rate": 0.1991591992641169, "num_layers": 1, "ff_dim": 512, "batch_size": 32, "l2_reg": 0.00027921040976332896, "lookback": 30, "sequence_length": 30}, "time_since_restore": 2.2837905883789062, "iterations_since_restore": 1}
{"loss": 0.6197577714920044, "timestamp": 1742322832, "checkpoint_dir_name": null, "done": false, "training_iteration": 2, "trial_id": "19edf_00203", "date": "2025-03-18_11-33-52", "time_this_iter_s": 0.0011126995086669922, "time_total_s": 2.2849032878875732, "pid": 32364, "hostname": "PS2023NAHFSMES", "node_ip": "127.0.0.1", "config": {"learning_rate": 1.059948063412498e-06, "num_heads": 2, "dropout_rate": 0.1991591992641169, "num_layers": 1, "ff_dim": 512, "batch_size": 32, "l2_reg": 0.00027921040976332896, "lookback": 30, "sequence_length": 30}, "time_since_restore": 2.2849032878875732, "iterations_since_restore": 2}
