{"loss": 0.2549249529838562, "timestamp": 1742181983, "checkpoint_dir_name": null, "done": false, "training_iteration": 1, "trial_id": "5ad74_00010", "date": "2025-03-16_20-26-23", "time_this_iter_s": 4.335589647293091, "time_total_s": 4.335589647293091, "pid": 32188, "hostname": "PS2023NAHFSMES", "node_ip": "127.0.0.1", "config": {"learning_rate": 0.0001285759775309435, "num_heads": 4, "dropout_rate": 0.1356816533634982, "num_layers": 2, "ff_dim": 512, "batch_size": 64, "l2_reg": 0.0004162552125345687, "lookback": 30, "sequence_length": 30}, "time_since_restore": 4.335589647293091, "iterations_since_restore": 1}
{"loss": 0.2549249529838562, "timestamp": 1742181983, "checkpoint_dir_name": null, "done": false, "training_iteration": 2, "trial_id": "5ad74_00010", "date": "2025-03-16_20-26-23", "time_this_iter_s": 0.0, "time_total_s": 4.335589647293091, "pid": 32188, "hostname": "PS2023NAHFSMES", "node_ip": "127.0.0.1", "config": {"learning_rate": 0.0001285759775309435, "num_heads": 4, "dropout_rate": 0.1356816533634982, "num_layers": 2, "ff_dim": 512, "batch_size": 64, "l2_reg": 0.0004162552125345687, "lookback": 30, "sequence_length": 30}, "time_since_restore": 4.335589647293091, "iterations_since_restore": 2}
