{"loss": 0.6922712326049805, "timestamp": 1741863695, "checkpoint_dir_name": null, "done": false, "training_iteration": 1, "trial_id": "4ec47_00456", "date": "2025-03-13_04-01-35", "time_this_iter_s": 9.56063199043274, "time_total_s": 9.56063199043274, "pid": 21996, "hostname": "PS2023NAHFSMES", "node_ip": "127.0.0.1", "config": {"learning_rate": 0.000135222646212699, "num_heads": 4, "dropout_rate": 0.34611474935534625, "num_layers": 3, "ff_dim": 256, "batch_size": 16, "l2_reg": 2.0744397723419923e-05}, "time_since_restore": 9.56063199043274, "iterations_since_restore": 1}
