{"loss": 0.046680305153131485, "timestamp": 1742725284, "checkpoint_dir_name": null, "done": false, "training_iteration": 1, "trial_id": "dfdca_01922", "date": "2025-03-23_03-21-24", "time_this_iter_s": 11.348028182983398, "time_total_s": 11.348028182983398, "pid": 26500, "hostname": "PS2023NAHFSMES", "node_ip": "127.0.0.1", "config": {"learning_rate": 0.0007535014124895449, "num_heads": 8, "dropout_rate": 0.4219361311205221, "num_layers": 3, "ff_dim": 256, "batch_size": 16, "l2_reg": 0.0007728032325182345, "lookback": 30, "sequence_length": 30}, "time_since_restore": 11.348028182983398, "iterations_since_restore": 1}
{"loss": 0.046680305153131485, "timestamp": 1742725284, "checkpoint_dir_name": null, "done": false, "training_iteration": 2, "trial_id": "dfdca_01922", "date": "2025-03-23_03-21-24", "time_this_iter_s": 0.001226663589477539, "time_total_s": 11.349254846572876, "pid": 26500, "hostname": "PS2023NAHFSMES", "node_ip": "127.0.0.1", "config": {"learning_rate": 0.0007535014124895449, "num_heads": 8, "dropout_rate": 0.4219361311205221, "num_layers": 3, "ff_dim": 256, "batch_size": 16, "l2_reg": 0.0007728032325182345, "lookback": 30, "sequence_length": 30}, "time_since_restore": 11.349254846572876, "iterations_since_restore": 2}
