{"loss": Infinity, "timestamp": 1742456684, "checkpoint_dir_name": null, "done": false, "training_iteration": 1, "trial_id": "94582_00281", "date": "2025-03-20_00-44-44", "time_this_iter_s": 0.1036529541015625, "time_total_s": 0.1036529541015625, "pid": 31988, "hostname": "PS2023NAHFSMES", "node_ip": "127.0.0.1", "config": {"learning_rate": 0.00015683852581586645, "num_heads": 8, "dropout_rate": 0.3394633936788146, "num_layers": 3, "ff_dim": 512, "batch_size": 16, "l2_reg": 0.0016445845403801217, "lookback": 30, "sequence_length": 90}, "time_since_restore": 0.1036529541015625, "iterations_since_restore": 1}
