{"loss": 1.4762861728668213, "test_loss": 1.9385112524032593, "timestamp": 1741932172, "checkpoint_dir_name": null, "done": false, "training_iteration": 1, "trial_id": "d5b58_00003", "date": "2025-03-13_23-02-52", "time_this_iter_s": 6.792337417602539, "time_total_s": 6.792337417602539, "pid": 21260, "hostname": "PS2023NAHFSMES", "node_ip": "127.0.0.1", "config": {"learning_rate": 1.2784413175631373e-06, "num_heads": 2, "dropout_rate": 0.36584409036827426, "num_layers": 3, "ff_dim": 256, "batch_size": 64, "l2_reg": 0.0007266112953877004}, "time_since_restore": 6.792337417602539, "iterations_since_restore": 1}
