{"loss": 0.8175734281539917, "test_loss": 0.5986435413360596, "timestamp": 1741946173, "checkpoint_dir_name": null, "done": false, "training_iteration": 1, "trial_id": "450d7_00397", "date": "2025-03-14_02-56-13", "time_this_iter_s": 5.69035267829895, "time_total_s": 5.69035267829895, "pid": 18204, "hostname": "PS2023NAHFSMES", "node_ip": "127.0.0.1", "config": {"learning_rate": 5.070488696510287e-05, "num_heads": 4, "dropout_rate": 0.3988635906958621, "num_layers": 2, "ff_dim": 128, "batch_size": 64, "l2_reg": 0.00011480662324767181}, "time_since_restore": 5.69035267829895, "iterations_since_restore": 1}
